frinZrs-0.1.5.dist-info/METADATA
frinZrs-0.1.5.dist-info/WHEEL
frinZrs/__init__.py
frinZrs/frinZrs.cpython-311-x86_64-linux-gnu.so
frinZrs-0.1.5.dist-info/RECORD
