Metadata-Version: 2.4
Name: frinZrs
Version: 0.1.5
Classifier: Programming Language :: Python :: 3
Classifier: Programming Language :: Rust
Classifier: Operating System :: OS Independent
Summary: A Python binding for reading VLBI spectrum data using Rust
Author-email: Masanori AKIMOTO <masanori.akimoto.ac@gmail.com>
License: MIT
Requires-Python: >=3.8
